conduit/cli/__init__.py
conduit/cli/main.py
conduit/cli/commands/__init__.py
conduit/cli/commands/confluence.py
conduit/cli/commands/jira.py
conduit/config/__init__.py
conduit/config/config.yaml
conduit/core/__init__.py
conduit/core/config.py
conduit/core/content.py
conduit/core/exceptions.py
conduit/core/logger.py
conduit/core/services.py
conduit/mcp/__init__.py
conduit/mcp/server.py
conduit/platforms/__init__.py
conduit/platforms/base.py
conduit/platforms/registry.py
conduit/platforms/confluence/__init__.py
conduit/platforms/confluence/client.py
conduit/platforms/confluence/config.py
conduit/platforms/confluence/content.py
conduit/platforms/jira/__init__.py
conduit/platforms/jira/client.py
conduit/platforms/jira/config.py
conduit/platforms/jira/content.py
conduit/ui/__init__.py
conduit/ui/app.py
conduit/ui/pages/__init__.py
conduit/ui/pages/atlassian.py
conduit_connect-0.1.19.dist-info/METADATA
conduit_connect-0.1.19.dist-info/WHEEL
conduit_connect-0.1.19.dist-info/entry_points.txt
conduit_connect-0.1.19.dist-info/top_level.txt
conduit_connect-0.1.19.dist-info/RECORD
