Metadata-Version: 2.4
Name: conduit-connect
Version: 0.1.19
Summary: Enterprise Knowledge Integration Service
Author-email: Tim Kitchens <codingthefuturewithai@gmail.com>
License: MIT
Keywords: jira,confluence,atlassian,integration,cli
Classifier: Development Status :: 3 - Alpha
Classifier: Intended Audience :: Developers
Classifier: License :: OSI Approved :: MIT License
Classifier: Programming Language :: Python :: 3
Classifier: Programming Language :: Python :: 3.10
Classifier: Programming Language :: Python :: 3.11
Classifier: Programming Language :: Python :: 3.12
Classifier: Topic :: Software Development :: Libraries :: Python Modules
Requires-Python: <3.13,>=3.10
Requires-Dist: atlassian-python-api>=3.41.0
Requires-Dist: pydantic>=2.0.0
Requires-Dist: click>=8.1.0
Requires-Dist: rich>=13.0.0
Requires-Dist: PyYAML>=6.0.1
Requires-Dist: requests>=2.31.0
Requires-Dist: beautifulsoup4>=4.12.0
Requires-Dist: lxml>=4.9.0
Requires-Dist: mcp>=1.0.0
Requires-Dist: mcp[cli]>=1.0.0
Requires-Dist: anyio>=4.5
Requires-Dist: starlette>=0.36.0
Requires-Dist: uvicorn>=0.27.0
Requires-Dist: md2cf>=2.3.0
Provides-Extra: dev
Requires-Dist: pytest>=7.4.0; extra == "dev"
Requires-Dist: pytest-cov>=4.1.0; extra == "dev"
Requires-Dist: black>=23.7.0; extra == "dev"
Requires-Dist: isort>=5.12.0; extra == "dev"
Requires-Dist: mypy>=1.4.1; extra == "dev"
Requires-Dist: ruff>=0.0.284; extra == "dev"
Requires-Dist: build; extra == "dev"
